torchfa/__init__.py
torchfa/dataset.py
torchfa/torchfa.py
torchfa/utils.py
torchfa-0.1.1.dist-info/licenses/LICENSE
torchfa-0.1.1.dist-info/METADATA
torchfa-0.1.1.dist-info/WHEEL
torchfa-0.1.1.dist-info/top_level.txt
torchfa-0.1.1.dist-info/RECORD
