Metadata-Version: 2.4
Name: torchfa
Version: 0.1.1
Summary: TorchAudio Forced Aligner
Author-email: Zhendong Peng <pzd17@tsinghua.org.cn>
License: MIT License
Project-URL: Homepage, https://github.com/pengzhendong/torchfa
Project-URL: Documentation, https://github.com/pengzhendong/torchfa#readme
Project-URL: BugTracker, https://github.com/pengzhendong/torchfa/issues
Classifier: Programming Language :: Python :: 3
Classifier: Operating System :: OS Independent
Requires-Python: >=3.8
License-File: LICENSE
Requires-Dist: g2p-mix
Requires-Dist: lhotse
Requires-Dist: tgt
Requires-Dist: torch
Requires-Dist: torchaudio
Dynamic: license-file
